{"chunk_definitions":[{"chunk_id":"cc617883lpsu1","expansion_state":0,"options":[],"row":23,"row_count":1,"visible":true},{"chunk_id":"cr15zklcp6n6l","expansion_state":0,"options":[],"row":50,"row_count":1,"visible":true},{"chunk_id":"cpqrcs6sd4vn8","expansion_state":0,"options":[],"row":66,"row_count":1,"visible":true},{"chunk_id":"cgtqfqehv5uu2","expansion_state":0,"options":[],"row":76,"row_count":1,"visible":true},{"chunk_id":"clx2m4rvnwx91","expansion_state":0,"options":[],"row":91,"row_count":1,"visible":true},{"chunk_id":"co8npkydm7h7m","expansion_state":0,"options":[],"row":141,"row_count":1,"visible":true},{"chunk_id":"c2id0e5wg1r3h","expansion_state":0,"options":[],"row":209,"row_count":1,"visible":true},{"chunk_id":"cikr8jk9897kd","expansion_state":0,"options":[],"row":261,"row_count":1,"visible":true},{"chunk_id":"cvtoqis0rlqyz","expansion_state":0,"options":[],"row":330,"row_count":1,"visible":true},{"chunk_id":"cvw8v6nbv9yk1","expansion_state":0,"options":[],"row":378,"row_count":1,"visible":true},{"chunk_id":"cq8k54uatkpvs","expansion_state":0,"options":[],"row":445,"row_count":1,"visible":true}],"doc_write_time":1596520771.95776}
